COPYING
MANIFEST.in
README
health_insurance_view.xml
setup.py
./__init__.py
./health_insurance.py
./health_insurance_view.xml
./tryton.cfg
./doc/index.rst
./locale/ar.po
./locale/de.po
./locale/el.po
./locale/es.po
./locale/fr.po
./locale/it_IT.po
./locale/ja_JP.po
./locale/lo.po
./locale/pt_BR.po
./locale/zh_CN.po
./tests/__init__.py
./tests/test_health_insurance.py
./view/gnuhealth_health_service.xml
./view/gnuhealth_insurance_plan.xml
./view/gnuhealth_insurance_plan_product_policy.xml
./view/gnuhealth_insurance_plan_product_policy_tree.xml
./wizard/__init__.py
./wizard/wizard_health_insurance.py
locale/ar.po
locale/de.po
locale/el.po
locale/es.po
locale/fr.po
locale/it_IT.po
locale/ja_JP.po
locale/lo.po
locale/pt_BR.po
locale/zh_CN.po
trytond_health_insurance.egg-info/PKG-INFO
trytond_health_insurance.egg-info/SOURCES.txt
trytond_health_insurance.egg-info/dependency_links.txt
trytond_health_insurance.egg-info/entry_points.txt
trytond_health_insurance.egg-info/not-zip-safe
trytond_health_insurance.egg-info/requires.txt
trytond_health_insurance.egg-info/top_level.txt
view/gnuhealth_health_service.xml
view/gnuhealth_insurance_plan.xml
view/gnuhealth_insurance_plan_product_policy.xml
view/gnuhealth_insurance_plan_product_policy_tree.xml